json_home_client/__init__.py
json_home_client/client.py
json_home_client/py.typed
json_home_client-1.1.1.dist-info/LICENSE
json_home_client-1.1.1.dist-info/METADATA
json_home_client-1.1.1.dist-info/WHEEL
json_home_client-1.1.1.dist-info/top_level.txt
json_home_client-1.1.1.dist-info/RECORD
