Metadata-Version: 2.1
Name: json-home-client
Version: 1.1.1
Summary: Client for REST APIs using JSON Home pages per https://tools.ietf.org/html/draft-nottingham-json-home-06
Home-page: https://github.com/plinss/json_home_client/
Author: Peter Linss
Author-email: pypi@linss.com
License: UNKNOWN
Platform: UNKNOWN
Classifier: Programming Language :: Python :: 3
Classifier: License :: OSI Approved :: MIT License
Classifier: Operating System :: OS Independent
Requires-Python: >=3.6
Requires-Dist: uri-template
Provides-Extra: dev
Requires-Dist: mypy ; extra == 'dev'
Requires-Dist: flake8 ; extra == 'dev'
Requires-Dist: flake8-import-order ; extra == 'dev'
Requires-Dist: flake8-annotations ; extra == 'dev'
Requires-Dist: flake8-type-annotations ; extra == 'dev'
Requires-Dist: flake8-docstrings ; extra == 'dev'
Requires-Dist: pep8-naming ; extra == 'dev'
